odoo10_addon_web_domain_field-10.0.1.0.0-py2.7-nspkg.pth
odoo/addons/web_domain_field/README.rst
odoo/addons/web_domain_field/__init__.py
odoo/addons/web_domain_field/__manifest__.py
odoo/addons/web_domain_field/static/description/icon.png
odoo/addons/web_domain_field/static/src/js/pyeval.js
odoo/addons/web_domain_field/views/web_domain_field.xml
odoo10_addon_web_domain_field-10.0.1.0.0.dist-info/DESCRIPTION.rst
odoo10_addon_web_domain_field-10.0.1.0.0.dist-info/METADATA
odoo10_addon_web_domain_field-10.0.1.0.0.dist-info/RECORD
odoo10_addon_web_domain_field-10.0.1.0.0.dist-info/WHEEL
odoo10_addon_web_domain_field-10.0.1.0.0.dist-info/metadata.json
odoo10_addon_web_domain_field-10.0.1.0.0.dist-info/namespace_packages.txt
odoo10_addon_web_domain_field-10.0.1.0.0.dist-info/top_level.txt
